methylgpt/__init__.py
methylgpt/common_setup.py
methylgpt/finetuning/__init__.py
methylgpt/finetuning/__pycache__/__init__.cpython-39.pyc
methylgpt/finetuning/__pycache__/methyl_finetuning_models.cpython-39.pyc
methylgpt/finetuning/finetuning_metrics.py
methylgpt/finetuning/methyl_finetuning_datasets.py
methylgpt/finetuning/methyl_finetuning_models.py
methylgpt/methylGPT.egg-info/PKG-INFO
methylgpt/methylGPT.egg-info/SOURCES.txt
methylgpt/methylGPT.egg-info/dependency_links.txt
methylgpt/methylGPT.egg-info/top_level.txt
methylgpt/model/__init__.py
methylgpt/model/__pycache__/__init__.cpython-39.pyc
methylgpt/model/__pycache__/methyl_datasets.cpython-39.pyc
methylgpt/model/__pycache__/methyl_loss.cpython-39.pyc
methylgpt/model/__pycache__/methyl_model.cpython-39.pyc
methylgpt/model/__pycache__/methyl_vocab.cpython-39.pyc
methylgpt/model/loss_function
methylgpt/model/methyl_datasets.py
methylgpt/model/methyl_loss.py
methylgpt/model/methyl_model.py
methylgpt/model/methyl_pretraining.py
methylgpt/model/methyl_vocab.py
methylgpt/modules/__init__.py
methylgpt/modules/__pycache__/__init__.cpython-39.pyc
methylgpt/modules/scGPT/.readthedocs.yaml
methylgpt/modules/scGPT/.vscode/launch.json
methylgpt/modules/scGPT/.vscode/settings.json
methylgpt/modules/scGPT/LICENSE
methylgpt/modules/scGPT/README.md
methylgpt/modules/scGPT/data/README.md
methylgpt/modules/scGPT/data/cellxgene/README.md
methylgpt/modules/scGPT/data/cellxgene/array_build_scb.sh
methylgpt/modules/scGPT/data/cellxgene/array_download_partition.sh
methylgpt/modules/scGPT/data/cellxgene/array_process_allcounts.sh
methylgpt/modules/scGPT/data/cellxgene/build_large_scale_data.py
methylgpt/modules/scGPT/data/cellxgene/build_soma_idx.py
methylgpt/modules/scGPT/data/cellxgene/build_soma_idx.sh
methylgpt/modules/scGPT/data/cellxgene/cancer_list.txt
methylgpt/modules/scGPT/data/cellxgene/data_config.py
methylgpt/modules/scGPT/data/cellxgene/download_partition.py
methylgpt/modules/scGPT/data/cellxgene/download_partition.sh
methylgpt/modules/scGPT/data/cellxgene/expand_gene_list.py
methylgpt/modules/scGPT/data/cellxgene/metainfo.json
methylgpt-0.1.2.dist-info/LICENSE
methylgpt-0.1.2.dist-info/METADATA
methylgpt-0.1.2.dist-info/WHEEL
methylgpt-0.1.2.dist-info/RECORD
