Metadata-Version: 2.3
Name: methylgpt
Version: 0.1.2
Summary: 
Author: Jinyeop Song
Author-email: you@example.com
Requires-Python: >=3.9,<4.0
Classifier: Programming Language :: Python :: 3
Classifier: Programming Language :: Python :: 3.9
Classifier: Programming Language :: Python :: 3.10
Classifier: Programming Language :: Python :: 3.11
Classifier: Programming Language :: Python :: 3.12
Classifier: Programming Language :: Python :: 3.13
Requires-Dist: datasets (==2.21.0)
Requires-Dist: leidenalg (==0.10.2)
Requires-Dist: numba (==0.60.0)
Requires-Dist: pandas (>=2.2.2,<3.0.0)
Requires-Dist: psutil (==6.1.0)
Requires-Dist: scanpy (==1.9.8)
Requires-Dist: scib (==1.1.5)
Requires-Dist: scikit-misc (==0.3.1)
Requires-Dist: scvi-tools (==1.1.5)
Requires-Dist: torch (==2.0.1)
Requires-Dist: torchtext (==0.15.2)
Requires-Dist: typing-extensions (==4.12.2)
Requires-Dist: umap-learn (==0.5.6)
Requires-Dist: yarrowformat (==1.2.0)
